MANIFEST.in
README.txt
setup.py
ArenaPy.egg-info/PKG-INFO
ArenaPy.egg-info/SOURCES.txt
ArenaPy.egg-info/dependency_links.txt
ArenaPy.egg-info/not-zip-safe
ArenaPy.egg-info/requires.txt
ArenaPy.egg-info/top_level.txt
arenapy/__init__.py
arenapy/arenapy.py