Metadata-Version: 1.0
Name: ArenaPy
Version: 0.1.0
Summary: A simple python interface to the Are.na api
Home-page: https://github.com/jnhasty/arenapy
Author: jnhasty
Author-email: jnhasty@gmail.com
License: MIT
Keywords: arena rest api client
Platform: UNKNOWN
Classifier: License :: OSI Approved :: MIT License
Classifier: Programming Language :: Python
Classifier: Development Status :: 4 - Beta
Classifier: Intended Audience :: Developers
Classifier: Topic :: Internet :: WWW/HTTP
